README.md
setup.py
src/concurrent_decorator/__init__.py
src/concurrent_decorator/concurrent_decorator.py
src/concurrent_decorator.egg-info/PKG-INFO
src/concurrent_decorator.egg-info/SOURCES.txt
src/concurrent_decorator.egg-info/dependency_links.txt
src/concurrent_decorator.egg-info/top_level.txt